{
  "componentType": "corespring-drag-and-drop-inline",
  "title": "Short Answer - Drag and Drop",
  "correctResponse": {
    "aa_1": []
  },
  "feedback": {
    "correctFeedbackType": "default",
    "partialFeedbackType": "default",
    "incorrectFeedbackType": "default"
  },
  "allowPartialScoring": false,
  "partialScoring" : [
    {}
  ],
  "model": {
    "answerAreas": [
      {
        "id": "aa_1",
        "textBefore": "",
        "textAfter": ""
      }
    ],
    "choices": [
      {
        "label": "",
        "labelType": "text",
        "id": "choice_0"
      },
      {
        "label": "",
        "labelType": "text",
        "id": "choice_1"
      },
      {
        "label": "",
        "labelType": "text",
        "id": "choice_2"
      },
      {
        "label": "",
        "labelType": "text",
        "id": "choice_3"
      }
    ],
    "config": {
      "shuffle": false,
      "choiceAreaLabel": "Choices",
      "choiceAreaLayout": "horizontal",
      "choiceAreaPosition": "below"
    }
  },
  "weight": 1
}